README.rst
screenshot.png
setup.py
transition.zip
docs/HISTORY.txt
docs/INSTALL.txt
docs/LICENSE.GPL
docs/LICENSE.txt
plonetheme/__init__.py
plonetheme.transition.egg-info/PKG-INFO
plonetheme.transition.egg-info/SOURCES.txt
plonetheme.transition.egg-info/dependency_links.txt
plonetheme.transition.egg-info/entry_points.txt
plonetheme.transition.egg-info/namespace_packages.txt
plonetheme.transition.egg-info/requires.txt
plonetheme.transition.egg-info/top_level.txt
plonetheme/transition/__init__.py
plonetheme/transition/configure.zcml
plonetheme/transition/profiles/default/metadata.xml
plonetheme/transition/profiles/default/theme.xml
plonetheme/transition/static/default.css
plonetheme/transition/static/index.html
plonetheme/transition/static/license.txt
plonetheme/transition/static/manifest.cfg
plonetheme/transition/static/plonetheme.css
plonetheme/transition/static/rules.xml
plonetheme/transition/static/images/img01.gif
plonetheme/transition/static/images/img02.gif
plonetheme/transition/static/images/img03.jpg
plonetheme/transition/static/images/img04.jpg
plonetheme/transition/static/images/img05.gif
plonetheme/transition/static/images/img06.gif
plonetheme/transition/static/images/img07.gif
plonetheme/transition/static/images/img08.gif
plonetheme/transition/static/images/img10.gif
plonetheme/transition/static/images/img11.gif
plonetheme/transition/static/images/x.jpg