Metadata-Version: 1.0
Name: plonetheme.transition
Version: 1.2
Summary: An installable Diazo theme for Plone 4.1
Home-page: http://github.com/gyst/plonetheme.transition
Author: Guido Stevens
Author-email: guido.stevens@cosent.net
License: UNKNOWN
Platform: UNKNOWN
Classifier: Framework :: Plone
Classifier: Programming Language :: Python
